fantasy_nba_israel_mcp/__init__.py
fantasy_nba_israel_mcp/__main__.py
fantasy_nba_israel_mcp/api_client.py
fantasy_nba_israel_mcp/filters.py
fantasy_nba_israel_mcp/server.py
fantasy_nba_israel_mcp-0.3.6.dist-info/METADATA
fantasy_nba_israel_mcp-0.3.6.dist-info/WHEEL
fantasy_nba_israel_mcp-0.3.6.dist-info/entry_points.txt
fantasy_nba_israel_mcp-0.3.6.dist-info/RECORD
