Metadata-Version: 2.4
Name: fantasy-nba-israel-mcp
Version: 0.3.6
Summary: A Model Context Protocol server for accessing our Fantasy NBA League statistics and rankings
Project-URL: Homepage, https://github.com/AsafShai/nba-fantasy-israel-mcp
Project-URL: Repository, https://github.com/AsafShai/nba-fantasy-israel-mcp
Project-URL: Documentation, https://github.com/AsafShai/nba-fantasy-israel-mcp#readme
Author-email: Asaf Shai <asafshai211@gmail.com>
Maintainer-email: Asaf Shai <asafshai211@gmail.com>
Keywords: basketball,fantasy,league,mcp,model-context-protocol,nba,rankings,statistics
Classifier: Development Status :: 3 - Alpha
Classifier: Intended Audience :: Developers
Classifier: Programming Language :: Python :: 3
Classifier: Programming Language :: Python :: 3.10
Classifier: Programming Language :: Python :: 3.11
Classifier: Programming Language :: Python :: 3.12
Classifier: Programming Language :: Python :: 3.13
Classifier: Topic :: Games/Entertainment
Classifier: Topic :: Software Development :: Libraries :: Python Modules
Requires-Python: >=3.10
Requires-Dist: httpx>=0.28.1
Requires-Dist: mcp[cli]>=1.18.0
